odoo10_addon_l10n_br_data_base-10.0.1.0.0-py2.7-nspkg.pth
odoo10_addon_l10n_br_data_base-10.0.1.0.0.dist-info/top_level.txt
odoo10_addon_l10n_br_data_base-10.0.1.0.0.dist-info/WHEEL
odoo10_addon_l10n_br_data_base-10.0.1.0.0.dist-info/RECORD
odoo10_addon_l10n_br_data_base-10.0.1.0.0.dist-info/metadata.json
odoo10_addon_l10n_br_data_base-10.0.1.0.0.dist-info/DESCRIPTION.rst
odoo10_addon_l10n_br_data_base-10.0.1.0.0.dist-info/METADATA
odoo10_addon_l10n_br_data_base-10.0.1.0.0.dist-info/namespace_packages.txt
odoo/addons/l10n_br_data_base/__manifest__.py
odoo/addons/l10n_br_data_base/__init__.py
odoo/addons/l10n_br_data_base/README.rst
odoo/addons/l10n_br_data_base/i18n/pt_BR.po
odoo/addons/l10n_br_data_base/data/res.bank.csv
odoo/addons/l10n_br_data_base/static/description/icon.png
